task3/ram.sv
module ram2ports #(
    parameter ADDRESS_WIDTH = 8,
              DATA_WIDTH = 8
)(
    input logic                       clk,
    input logic                      wr_en,
    input logic                      rd_en,
    input logic [ADDRESS_WIDTH-1:0] wr_addr,
    input logic [ADDRESS_WIDTH-1:0] rd_addr,
    input logic [ADDRESS_WIDTH-1:0]     din,
    output logic [ADDRESS_WIDTH-1:0]   dout
);

logic [DATA_WIDTH-1:0]  ram_array [2**ADDRESS_WIDTH-1:0];

always_ff @(posedge clk) begin
    if(wr_en == 1'b1)
        ram_array[wr_en] <= din;
    if(rd_en == 1'b1)
        dout <= ram_array [rd_addr];
end
endmodule

task3/counter.sv
module counter #(
    parameter WIDTH = 8
)(
    // interface signals
    input logic [7:0]          incr,    //input incr
    input logic                clk,     // clock
    input logic                rst,     // reset
    input logic                 en,     //counter enable
    output logic [WIDTH-1:0] count     // count output
);

always_ff @ (posedge clk)
    if (rst) count <= {WIDTH{1'b0}}; 
    else if(en) 
        count <= count + incr;
endmodule

task3/sigdelay.sv
module sigdelay #(
    parameter   A_WIDTH = 8,
                D_WIDTH = 8
)(
    //interface signal
    input logic [D_WIDTH-1:0]    incr,
    input logic                  rst,
    input logic                  en,
    input logic                  clk,
    input logic [D_WIDTH-1:0]    offset,
    input logic                  wr,
    input logic                  rd,
    input logic                 mic_signal,
    output logic [D_WIDTH-1:0]   delayed_signal,
);

    logic  [A_WIDTH-1:0]        address1;
    counter addrCounter(
        .incr(incr),
        .clk(clk),
        .rst(rst),
        .en(en),
        .count(address1)
    );
    ram2ports sineRam(
        .clk(clk),
        .wr_en(wr),
        .rd_en(rd),
        .rd_addr(address1 +offset),
        .wr_addr(address1),
        .din({(D_WIDTH-1){mic_signal}}),
        .dout(delayed_signal)
    );

endmodule

task3/sigdelay.vcd
$version Generated by VerilatedVcd $end
$date Sat Oct 26 21:53:30 2024 $end
$timescale 1ps $end

 $scope module TOP $end
  $var wire  1 & clk $end
  $var wire  8 + delayed_signal [7:0] $end
  $var wire  1 % en $end
  $var wire  8 # incr [7:0] $end
  $var wire  1 * mic_signal $end
  $var wire  8 ' offset [7:0] $end
  $var wire  1 ) rd $end
  $var wire  1 $ rst $end
  $var wire  1 ( wr $end
  $scope module sigdelay $end
   $var wire 32 / A_WIDTH [31:0] $end
   $var wire 32 / D_WIDTH [31:0] $end
   $var wire  8 , address1 [7:0] $end
   $var wire  1 & clk $end
   $var wire  8 + delayed_signal [7:0] $end
   $var wire  1 % en $end
   $var wire  8 # incr [7:0] $end
   $var wire  1 * mic_signal $end
   $var wire  8 ' offset [7:0] $end
   $var wire  1 ) rd $end
   $var wire  1 $ rst $end
   $var wire  1 ( wr $end
   $scope module addrCounter $end
    $var wire 32 / WIDTH [31:0] $end
    $var wire  1 & clk $end
    $var wire  8 , count [7:0] $end
    $var wire  1 % en $end
    $var wire  8 # incr [7:0] $end
    $var wire  1 $ rst $end
   $upscope $end
   $scope module sineRam $end
    $var wire 32 / ADDRESS_WIDTH [31:0] $end
    $var wire 32 / DATA_WIDTH [31:0] $end
    $var wire  1 & clk $end
    $var wire  8 . din [7:0] $end
    $var wire  8 + dout [7:0] $end
    $var wire  8 - rd_addr [7:0] $end
    $var wire  1 ) rd_en $end
    $var wire  8 , wr_addr [7:0] $end
    $var wire  1 ( wr_en $end
   $upscope $end
  $upscope $end
 $upscope $end
$enddefinitions $end


#0
b00000000 #
0$
0%
1&
b01000000 '
1(
1)
0*
b00000000 +
b00000000 ,
b01000000 -
b00000000 .
b00000000000000000000000000001000 /
#1
0&
#2
1&
b00000001 '
~*
b00000001 -
b00010010 .
#3
0&
#4
1&
s*
b00011101 .
#5
0&
#6
1&
b00010010 +
#7
0&
#8
1&
{*
b00011101 +
b00100101 .
#9
0&
#10
1&
x*
b00011000 .
#11
0&
#12
1&
}*
b00100101 +
b00110011 .
#13
0&
#14
1&
z*
b00011000 +
b00110110 .
#15
0&
#16
1&
v*
b00110011 +
b00011010 .
#17
0&
#18
1&
p*
b00110110 +
b00100000 .
#19
0&
#20
1&
>*
b00011010 +
b01000010 .
#21
0&
#22
1&
½*
b00100000 +
b01110011 .
#23
0&
#24
1&
}*
b01000010 +
b00110011 .
#25
0&
#26
1&
*
b01110011 +
b00100001 .
#27
0&
#28
1&
y*
b00110011 +
b00010111 .
#29
0&
#30
1&
»*
b00100001 +
b01100101 .
#31
0&
#32
1&
¾*
b00010111 +
b01110010 .
#33
0&
#34
1&
y*
b01100101 +
b00010111 .
#35
0&
#36
1&
x*
b01110010 +
b00011000 .
#37
0&
#38
1&
u*
b00010111 +
b00011011 .
#39
0&
#40
1&
~*
b00011000 +
b00100010 .
#41
0&
#42
1&
s*
b00011011 +
b00011101 .
#43
0&
#44
1&
}*
b00100010 +
b00100011 .
#45
0&
#46
1&
|*
b00011101 +
b00010100 .
#47
0&
#48
1&
*
b00100011 +
b00100001 .
#49
0&
#50
1&
z*
b00010100 +
b00100110 .
#51
0&
#52
1&
s*
b00100001 +
b00011101 .
#53
0&
#54
1&
|*
b00100110 +
b00010100 .
#55
0&
#56
1&
s*
b00011101 +
b00101101 .
#57
0&
#58
1&
*
b00010100 +
b00110001 .
#59
0&
#60
1&
z*
b00101101 +
b00010110 .
#61
0&
#62
1&
q*
b00110001 +
b00011111 .
#63
0&
#64
1&
~*
b00010110 +
b00110010 .
#65
0&
#66
1&
»*
b00011111 +
b01110101 .
#67
0&
#68
1&
{*
b00110010 +
b00110101 .
#69
0&
#70
1&
x*
b01110101 +
b00011000 .
#71
0&
#72
1&
t*
b00110101 +
b00001100 .
#73
0&
#74
1&
´*
b00011000 +
b01011100 .
#75
0&
#76
1&
²*
b00001100 +
b01111110 .
#77
0&
#78
1&
r*
b01011100 +
b00001110 .
#79
0&
#80
1&
q*
b01111110 +
b00001111 .
#81
0&
#82
1&
}*
b00001110 +
b00100011 .
#83
0&
#84
1&
z*
b00001111 +
b00010110 .
#85
0&
#86
1&
p*
b00100011 +
b00100000 .
#87
0&
#88
1&
~*
b00010110 +
b00010010 .
#89
0&
#90
1&
}*
b00100000 +
b00010011 .
#91
0&
#92
1&
x*
b00010010 +
b00011000 .
#93
0&
#94
1&
~*
b00010011 +
b00110010 .
#95
0&
#96
1&
|*
b00011000 +
b00010100 .
#97
0&
#98
1&
r*
b00110010 +
b00011110 .
#99
0&
#100
1&
t*
b00010100 +
b00101100 .
#101
0&
#102
1&
|*
b00011110 +
b00100100 .
#103
0&
#104
1&
~*
b00101100 +
b00010010 .
#105
0&
#106
1&
y*
b00100100 +
b00110111 .
#107
0&
#108
1&
x*
b00010010 +
b00001000 .
#109
0&
#110
1&
r*
b00110111 +
b00011110 .
#111
0&
#112
1&
x*
b00001000 +
b00111000 .
#113
0&
#114
1&
*
b00011110 +
b00010001 .
#115
0&
#116
1&
±*
b00111000 +
b01101111 .
#117
0&
#118
1&
³*
b00010001 +
b01011101 .
#119
0&
#120
1&
y*
b01101111 +
b00000111 .
#121
0&
#122
1&
t*
b01011101 +
b00001100 .
#123
0&
#124
1&
*
b00000111 +
b00010001 .
#125
0&
#126
1&
*
b00001100 +
b00100001 .
#127
0&
#128
1&
r*
b00010001 +
b00001110 .
#129
0&
#130
1&
p*
b00100001 +
b00100000 .
#131
0&
#132
1&
u*
b00001110 +
b00001011 .
#133
0&
#134
1&
|*
b00100000 +
b00010100 .
#135
0&
#136
1&
{*
b00001011 +
b00010101 .
#137
0&
#138
1&
r*
b00010100 +
b00101110 .
#139
0&
#140
1&
~*
b00010101 +
b00010010 .
#141
0&
#142
1&
v*
b00101110 +
b00101010 .
#143
0&
#144
1&
r*
b00010010 +
b00101110 .
#145
0&
#146
1&
v*
b00101010 +
b00011010 .
#147
0&
#148
1&
r*
b00101110 +
b00011110 .
#149
0&
#150
1&
p*
b00011010 +
b01000000 .
#151
0&
#152
1&
²*
b00011110 +
b01101110 .
#153
0&
#154
1&
q*
b01000000 +
b00101111 .
#155
0&
#156
1&
*
b01101110 +
b00100001 .
#157
0&
#158
1&
q*
b00101111 +
b00001111 .
#159
0&
#160
1&
´*
b00100001 +
b01011100 .
#161
0&
#162
1&
¼*
b00001111 +
b01100100 .
#163
0&
#164
1&
u*
b01011100 +
b00001011 .
#165
0&
#166
1&
p*
b01100100 +
b00010000 .
#167
0&
#168
1&
p*
b00001011 +
b00100000 .
#169
0&
#170
1&
r*
b00010000 +
b00011110 .
#171
0&
#172
1&
b00100000 +
#173
0&
#174
1&
{*
b00011110 +
b00100101 .
#175
0&
#176
1&
r*
b00001110 .
#177
0&
#178
1&
v*
b00100101 +
b00011010 .
#179
0&
#180
1&
u*
b00001110 +
b00101011 .
#181
0&
#182
1&
|*
b00011010 +
b00100100 .
#183
0&
#184
1&
u*
b00101011 +
b00011011 .
#185
0&
#186
1&
q*
b00100100 +
b00101111 .
#187
0&
#188
1&
r*
b00011011 +
b00101110 .
#189
0&
#190
1&
u*
b00101111 +
b00011011 .
#191
0&
#192
1&
v*
b00101110 +
b00101010 .
#193
0&
#194
1&
y*
b00011011 +
b00110111 .
#195
0&
#196
1&
³*
b00101010 +
b01111101 .
#197
0&
#198
1&
w*
b00110111 +
b00111001 .
#199
0&
#200
1&
v*
b01111101 +
b00011010 .
#201
0&
#202
1&
s*
b00111001 +
b00001101 .
#203
0&
#204
1&
°*
b00011010 +
b01100000 .
#205
0&
#206
1&
°*
b00001101 +
b00000000 .
#207
0&
#208
1&
r*
b01100000 +
b00001110 .
#209
0&
#210
1&
z*
b00000000 +
b00010110 .
#211
0&
#212
1&
{*
b00001110 +
b00100101 .
#213
0&
#214
1&
w*
b00010110 +
b00011001 .
#215
0&
#216
1&
p*
b00100101 +
b00100000 .
#217
0&
#218
1&
~*
b00011001 +
b00010010 .
#219
0&
#220
1&
*
b00100000 +
b00010001 .
#221
0&
#222
1&
r*
b00010010 +
b00011110 .
#223
0&
#224
1&
*
b00010001 +
b00110001 .
#225
0&
#226
1&
v*
b00011110 +
b00011010 .
#227
0&
#228
1&
u*
b00110001 +
b00011011 .
#229
0&
#230
1&
x*
b00011010 +
b00101000 .
#231
0&
#232
1&
b00011011 +
#233
0&
#234
1&
|*
b00101000 +
b00010100 .
#235
0&
#236
1&
r*
b00101110 .
#237
0&
#238
1&
z*
b00010100 +
b00010110 .
#239
0&
#240
1&
q*
b00101110 +
b00001111 .
#241
0&
#242
1&
v*
b00010110 +
b00111010 .
#243
0&
#244
1&
p*
b00001111 +
b00010000 .
#245
0&
#246
1&
¶*
b00111010 +
b01111010 .
#247
0&
#248
1&
½*
b00010000 +
b01010011 .
#249
0&
#250
1&
²*
b01111010 +
b01111110 .
#251
0&
#252
1&
|*
b01010011 +
b00000100 .
#253
0&
#254
1&
x*
b01111110 +
b00001000 .
#255
0&
#256
1&
s*
b00000100 +
b00011101 .
#257
0&
#258
1&
t*
b00001000 +
b00001100 .
#259
0&
#260
1&
v*
b00011101 +
b00011010 .
#261
0&
#262
1&
w*
b00001100 +
b00001001 .
#263
0&
#264
1&
q*
b00011010 +
b00001111 .
#265
0&
#266
1&
s*
b00001001 +
b00001101 .
#267
0&
#268
1&
|*
b00001111 +
b00100100 .
#269
0&
#270
1&
u*
b00001101 +
b00001011 .
#271
0&
#272
1&
q*
b00100100 +
b00011111 .
#273
0&
#274
1&
v*
b00001011 +
b00101010 .
#275
0&
#276
1&
q*
b00011111 +
b00011111 .
#277
0&
#278
1&
t*
b00101010 +
b00011100 .
#279
0&
#280
1&
s*
b00011111 +
b00111101 .
#281
0&
#282
1&
°*
b00011100 +
b01110000 .
#283
0&
#284
1&
r*
b00111101 +
b00101110 .
#285
0&
#286
1&
p*
b01110000 +
b00110000 .
#287
0&
#288
1&
x*
b00101110 +
b00011000 .
#289
0&
#290
1&
¹*
b00110000 +
b01100111 .
#291
0&
#292
1&
º*
b00011000 +
b01100110 .
#293
0&
#294
1&
*
b01100111 +
b00010001 .
#295
0&
#296
1&
s*
b01100110 +
b00001101 .
#297
0&
#298
1&
~*
b00010001 +
b00010010 .
#299
0&
#300
1&
y*
b00001101 +
b00010111 .
#301
0&
#302
1&
*
b00010010 +
b00010001 .
#303
0&
#304
1&
y*
b00010111 +
b00010111 .
#305
0&
#306
1&
y*
b00010001 +
b00000111 .
#307
0&
#308
1&
z*
b00010111 +
b00010110 .
#309
0&
#310
1&
*
b00000111 +
b00100001 .
#311
0&
#312
1&
b00010110 +
#313
0&
#314
1&
r*
b00100001 +
b00001110 .
#315
0&
#316
1&
|*
b00100100 .
#317
0&
#318
1&
v*
b00001110 +
b00101010 .
#319
0&
#320
1&
q*
b00100100 +
b00001111 .
#321
0&
#322
1&
v*
b00101010 +
b00011010 .
#323
0&
#324
1&
v*
b00001111 +
b00101010 .
#325
0&
#326
1&
¼*
b00011010 +
b01100100 .
#327
0&
#328
1&
u*
b00101010 +
b00101011 .
#329
0&
#330
1&
y*
b01100100 +
b00010111 .
#331
0&
#332
1&
t*
b00101011 +
b00001100 .
#333
0&
#334
1&
º*
b00010111 +
b01010110 .
#335
0&
#336
1&
½*
b00001100 +
b01110011 .
#337
0&
#338
1&
y*
b01010110 +
b00000111 .
#339
0&
#340
1&
t*
b01110011 +
b00001100 .
#341
0&
#342
1&
{*
b00000111 +
b00010101 .
#343
0&
#344
1&
v*
b00001100 +
b00001010 .
#345
0&
#346
1&
~*
b00010101 +
b00010010 .
#347
0&
#348
1&
s*
b00001010 +
b00001101 .
#349
0&
#350
1&
x*
b00010010 +
b00001000 .
#351
0&
#352
1&
y*
b00001101 +
b00010111 .
#353
0&
#354
1&
p*
b00001000 +
b00110000 .
#355
0&
#356
1&
y*
b00010111 +
b00010111 .
#357
0&
#358
1&
w*
b00110000 +
b00011001 .
#359
0&
#360
1&
w*
b00010111 +
b00101001 .
#361
0&
#362
1&
q*
b00011001 +
b00011111 .
#363
0&
#364
1&
|*
b00101001 +
b00010100 .
#365
0&
#366
1&
}*
b00011111 +
b00110011 .
#367
0&
#368
1&
v*
b00010100 +
b00011010 .
#369
0&
#370
1&
{*
b00110011 +
b00010101 .
#371
0&
#372
1&
s*
b00011010 +
b00111101 .
#373
0&
#374
1&
{*
b00010101 +
b00010101 .
#375
0&
#376
1&
²*
b00111101 +
b01111110 .
#377
0&
#378
1&
¿*
b00010101 +
b01100001 .
#379
0&
#380
1&
s*
b01111110 +
b00001101 .
#381
0&
#382
1&
p*
b01100001 +
b00010000 .
#383
0&
#384
1&
y*
b00001101 +
b00010111 .
#385
0&
#386
1&
}*
b00010000 +
b00100011 .
#387
0&
#388
1&
p*
b00010111 +
b00010000 .
#389
0&
#390
1&
q*
b00100011 +
b00011111 .
#391
0&
#392
1&
v*
b00010000 +
b00001010 .
#393
0&
#394
1&
|*
b00011111 +
b00010100 .
#395
0&
#396
1&
w*
b00001010 +
b00011001 .
#397
0&
#398
1&
}*
b00010100 +
b00110011 .
#399
0&
#400
1&
w*
b00011001 +
b00011001 .
#401
0&
#402
1&
r*
b00110011 +
b00101110 .
#403
0&
#404
1&
s*
b00011001 +
b00101101 .
#405
0&
#406
1&
}*
b00101110 +
b00010011 .
#407
0&
#408
1&
q*
b00101101 +
b00001111 .
#409
0&
#410
1&
{*
b00010011 +
b00110101 .
#411
0&
#412
1&
¶*
b00001111 +
b01111010 .
#413
0&
#414
1&
z*
b00110101 +
b00100110 .
#415
0&
#416
1&
p*
b01111010 +
b00110000 .
#417
0&
#418
1&
{*
b00100110 +
b00010101 .
#419
0&
#420
1&
µ*
b00110000 +
b01101011 .
#421
0&
#422
1&
¾*
b00010101 +
b01100010 .
#423
0&
#424
1&
b00000010 '
t*
b01101011 +
b00000010 -
b00001100 .
#425
0&
#426
1&
q*
b00000000 +
b00001111 .
#427
0&
#428
1&
}*
b00010011 .
#429
0&
#430
1&
t*
b00011100 .
#431
0&
#432
1&
b00000011 '
p*
b00000011 -
b00010000 .
#433
0&
#434
1&
t*
b00011100 .
#435
0&
#436
1&
b00000100 '
s*
b00000100 -
b00001101 .
#437
0&
#438
1&
s*
b00011101 .
#439
0&
#440
1&
|*
b00100100 .
#441
0&
#442
1&
b00000101 '
v*
b00000101 -
b00101010 .
#443
0&
#444
1&
{*
b00010101 .
#445
0&
#446
1&
s*
b00101101 .
#447
0&
#448
1&
q*
b00101111 .
#449
0&
#450
1&
b00000110 '
{*
b00000110 -
b00010101 .
#451
0&
#452
1&
v*
b00011010 .
#453
0&
#454
1&
u*
b00111011 .
#455
0&
#456
1&
°*
b01110000 .
#457
0&
#458
1&
}*
b00110011 .
#459
0&
#460
1&
*
b00100001 .
#461
0&
#462
1&
~*
b00010010 .
#463
0&
#464
1&
¾*
b01100010 .
#465
0&
#466
1&
»*
b01110101 .
#467
0&
#468
1&
~*
b00010010 .
#469
0&
#470
1&
#471
0&
#472
1&
t*
b00011100 .
#473
0&
#474
1&
w*
b00011001 .
#475
0&
#476
1&
y*
b00010111 .
#477
0&
#478
1&
*
b00010001 .
#479
0&
#480
1&
u*
b00001011 .
#481
0&
#482
1&
x*
b00011000 .
#483
0&
#484
1&
u*
b00101011 .
#485
0&
#486
1&
v*
b00011010 .
#487
0&
#488
1&
x*
b00011000 .
#489
0&
#490
1&
u*
b00101011 .
#491
0&
#492
1&
t*
b00101100 .
#493
0&
#494
1&
w*
b00011001 .
#495
0&
#496
1&
r*
b00101110 .
#497
0&
#498
1&
w*
b00011001 .
#499
0&
#500
1&
~*
b00000010 .
#501
0&
#502
1&
x*
b00111000 .
#503
0&
#504
1&
}*
b00010011 .
#505
0&
#506
1&
}*
b00000011 .
#507
0&
#508
1&
´*
b01011100 .
#509
0&
#510
1&
z*
b00000110 .
#511
0&
#512
1&
s*
b00001101 .
#513
0&
#514
1&
q*
b00001111 .
#515
0&
#516
1&
|*
b00100100 .
#517
0&
#518
1&
~*
b00010010 .
#519
0&
#520
1&
~*
b00100010 .
#521
0&
#522
1&
*
b00010001 .
#523
0&
#524
1&
~*
b00010010 .
#525
0&
#526
1&
{*
b00010101 .
#527
0&
#528
1&
t*
b00101100 .
#529
0&
#530
1&
p*
b00010000 .
#531
0&
#532
1&
*
b00100001 .
#533
0&
#534
1&
s*
b00101101 .
#535
0&
#536
1&
v*
b00011010 .
#537
0&
#538
1&
|*
b00010100 .
#539
0&
#540
1&
v*
b00111010 .
#541
0&
#542
1&
½*
b01110011 .
#543
0&
#544
1&
~*
b00100010 .
#545
0&
#546
1&
*
b00110001 .
#547
0&
#548
1&
{*
b00010101 .
#549
0&
#550
1&
²*
b01101110 .
#551
0&
#552
1&
¸*
b01101000 .
#553
0&
#554
1&
u*
b00001011 .
#555
0&
#556
1&
s*
b00001101 .
#557
0&
#558
1&
v*
b00011010 .
#559
0&
#560
1&
|*
b00100100 .
#561
0&
#562
1&
w*
b00011001 .
#563
0&
#564
1&
u*
b00101011 .
#565
0&
#566
1&
|*
b00010100 .
#567
0&
#568
1&
t*
b00011100 .
#569
0&
#570
1&
{*
b00100101 .
#571
0&
#572
1&
|*
b00100100 .
#573
0&
#574
1&
y*
b00010111 .
#575
0&
#576
1&
z*
b00110110 .
#577
0&
#578
1&
y*
b00110111 .
#579
0&
#580
1&
u*
b00011011 .
#581
0&
#582
1&
w*
b00101001 .
#583
0&
#584
1&
p*
b01000000 .
#585
0&
#586
1&
²*
b01101110 .
#587
0&
#588
1&
|*
b00110100 .
#589
0&
#590
1&
}*
b00100011 .
#591
0&
#592
1&
}*
b00010011 .
#593
0&
#594
1&
½*
b01100011 .
#595
0&
#596
1&
²*
b01111110 .
#597
0&
#598
1&
p*
b00010000 .
#599
0&
#600
1&
#601
0&
#602
1&
q*
b00011111 .
#603
0&
#604
1&
~*
b00010010 .
#605
0&
#606
1&
u*
b00011011 .
#607
0&
#608
1&
x*
b00011000 .
#609
0&
#610
1&
q*
b00001111 .
#611
0&
#612
1&
x*
b00011000 .
#613
0&
#614
1&
t*
b00101100 .
#615
0&
#616
1&
q*
b00001111 .
#617
0&
#618
1&
x*
b00011000 .
#619
0&
#620
1&
*
b00100001 .
#621
0&
#622
1&
p*
b00100000 .
#623
0&
#624
1&
s*
b00001101 .
#625
0&
#626
1&
z*
b00100110 .
#627
0&
#628
1&
z*
b00010110 .
#629
0&
#630
1&
x*
b00001000 .
#631
0&
#632
1&
~*
b00110010 .
#633
0&
#634
1&
~*
b00010010 .
#635
0&
#636
1&
¶*
b01111010 .
#637
0&
#638
1&
¼*
b01100100 .
#639
0&
#640
1&
s*
b00001101 .
#641
0&
#642
1&
y*
b00010111 .
#643
0&
#644
1&
x*
b00011000 .
#645
0&
#646
1&
z*
b00100110 .
#647
0&
#648
1&
}*
b00010011 .
#649
0&
#650
1&
r*
b00011110 .
#651
0&
#652
1&
s*
b00001101 .
#653
0&
#654
1&
v*
b00011010 .
#655
0&
#656
1&
u*
b00011011 .
#657
0&
#658
1&
y*
b00100111 .
#659
0&
#660
1&
r*
b00001110 .
#661
0&
#662
1&
y*
b00100111 .
#663
0&
#664
1&
z*
b00100110 .
#665
0&
#666
1&
y*
b00010111 .
#667
0&
#668
1&
}*
b00010011 .
#669
0&
#670
1&
y*
b00110111 .
#671
0&
#672
1&
¶*
b01101010 .
#673
0&
#674
1&
y*
b00100111 .
#675
0&
#676
1&
{*
b00100101 .
#677
0&
#678
1&
r*
b00001110 .
#679
0&
#680
1&
¾*
b01100010 .
#681
0&
#682
1&
¶*
b01101010 .
#683
0&
#684
1&
*
b00010001 .
#685
0&
#686
1&
}*
b00010011 .
#687
0&
#688
1&
u*
b00011011 .
#689
0&
#690
1&
q*
b00011111 .
#691
0&
#692
1&
z*
b00010110 .
#693
0&
#694
1&
w*
b00011001 .
#695
0&
#696
1&
{*
b00000101 .
#697
0&
#698
1&
|*
b00010100 .
#699
0&
#700
1&
q*
b00011111 .
#701
0&
#702
1&
t*
b00011100 .
#703
0&
#704
1&
*
b00010001 .
#705
0&
#706
1&
|*
b00100100 .
#707
0&
#708
1&
w*
b00101001 .
#709
0&
#710
1&
*
b00010001 .
#711
0&
#712
1&
*
b00100001 .
#713
0&
#714
1&
y*
b00110111 .
#715
0&
#716
1&
¶*
b01111010 .
#717
0&
#718
1&
w*
b00111001 .
#719
0&
#720
1&
u*
b00011011 .
#721
0&
#722
1&
w*
b00001001 .
#723
0&
#724
1&
¶*
b01011010 .
#725
0&
#726
1&
º*
b01110110 .
#727
0&
#728
1&
*
b00010001 .
#729
0&
#730
1&
~*
b00010010 .
#731
0&
#732
1&
*
b00100001 .
#733
0&
#734
1&
~*
b00010010 .
#735
0&
#736
1&
t*
b00011100 .
#737
0&
#738
1&
w*
b00001001 .
#739
0&
#740
1&
y*
b00000111 .
#741
0&
#742
1&
~*
b00010010 .
#743
0&
#744
1&
t*
b00101100 .
#745
0&
#746
1&
}*
b00010011 .
#747
0&
#748
1&
t*
b00011100 .
#749
0&
#750
1&
u*
b00101011 .
#751
0&
#752
1&
*
b00100001 .
#753
0&
#754
1&
}*
b00010011 .
#755
0&
#756
1&
~*
b00110010 .
#757
0&
#758
1&
t*
b00001100 .
#759
0&
#760
1&
}*
b00010011 .
#761
0&
#762
1&
t*
b00111100 .
#763
0&
#764
1&
y*
b00010111 .
#765
0&
#766
1&
²*
b01111110 .
#767
0&
#768
1&
½*
b01100011 .
#769
0&
#770
1&
t*
b00001100 .
#771
0&
#772
1&
q*
b00001111 .
#773
0&
#774
1&
}*
b00010011 .
#775
0&
#776
1&
p*
b00100000 .
#777
0&
#778
1&
~*
b00010010 .
#779
0&
#780
1&
|*
b00100100 .
#781
0&
#782
1&
r*
b00001110 .
#783
0&
#784
1&
z*
b00010110 .
#785
0&
#786
1&
y*
b00010111 .
#787
0&
#788
1&
v*
b00101010 .
#789
0&
#790
1&
u*
b00001011 .
#791
0&
#792
1&
{*
b00100101 .
#793
0&
#794
1&
y*
b00100111 .
#795
0&
#796
1&
w*
b00011001 .
#797
0&
#798
1&
}*
b00010011 .
#799
0&
#800
1&
~*
b00110010 .
#801
0&
#802
1&
º*
b01110110 .
#803
0&
#804
1&
u*
b00011011 .
#805
0&
#806
1&
u*
b00101011 .
#807
0&
#808
1&
}*
b00010011 .
#809
0&
#810
1&
·*
b01101001 .
#811
0&
#812
1&
¸*
b01101000 .
#813
0&
#814
1&
q*
b00001111 .
#815
0&
#816
1&
s*
b00001101 .
#817
0&
#818
1&
z*
b00010110 .
#819
0&
#820
1&
q*
b00011111 .
#821
0&
#822
1&
y*
b00010111 .
#823
0&
#824
1&
{*
b00100101 .
#825
0&
#826
1&
u*
b00001011 .
#827
0&
#828
1&
y*
b00010111 .
#829
0&
#830
1&
q*
b00011111 .
#831
0&
#832
1&
u*
b00011011 .
#833
0&
#834
1&
q*
b00001111 .
#835
0&
#836
1&
x*
b00101000 .
#837
0&
#838
1&
~*
b00110010 .
#839
0&
#840
1&
v*
b00011010 .
#841
0&
#842
1&
t*
b00011100 .
#843
0&
#844
1&
u*
b00111011 .
#845
0&
#846
1&
¹*
b01100111 .
#847
0&
#848
1&
r*
b00101110 .
#849
0&
#850
1&
x*
b00011000 .
#851
0&
#852
1&
u*
b00001011 .
#853
0&
#854
1&
²*
b01011110 .
#855
0&
#856
1&
¸*
b01111000 .
#857
0&
#858
1&
{*
b00010101 .
#859
0&
#860
1&
#861
0&
#862
1&
}*
b00100011 .
#863
0&
#864
1&
r*
b00011110 .
#865
0&
#866
1&
s*
b00011101 .
#867
0&
#868
1&
z*
b00010110 .
#869
0&
#870
1&
q*
b00001111 .
#871
0&
#872
1&
y*
b00010111 .
#873
0&
#874
1&
u*
b00101011 .
#875
0&
#876
1&
}*
b00010011 .
#877
0&
#878
1&
q*
b00011111 .
#879
0&
#880
1&
t*
b00101100 .
#881
0&
#882
1&
w*
b00101001 .
#883
0&
#884
1&
{*
b00010101 .
#885
0&
#886
1&
p*
b00110000 .
#887
0&
#888
1&
q*
b00001111 .
#889
0&
#890
1&
~*
b00010010 .
#891
0&
#892
1&
{*
b00010101 .
#893
0&
#894
1&
x*
b00011000 .
#895
0&
#896
1&
{*
b00010101 .
#897
0&
#898
1&
v*
b00011010 .
#899
0&
#900
1&
s*
b00011101 .
#901
0&
#902
1&
u*
b00011011 .
#903
0&
#904
1&
v*
b00011010 .
#905
0&
#906
1&
s*
b00011101 .
#907
0&
#908
1&
#909
0&
#910
1&
x*
b00011000 .
#911
0&
#912
1&
v*
b00011010 .
#913
0&
#914
1&
s*
b00011101 .
#915
0&
#916
1&
*
b00100001 .
#917
0&
#918
1&
r*
b00011110 .
#919
0&
#920
1&
#921
0&
#922
1&
v*
b00011010 .
#923
0&
#924
1&
w*
b00011001 .
#925
0&
#926
1&
#927
0&
#928
1&
t*
b00011100 .
#929
0&
#930
1&
v*
b00011010 .
#931
0&
#932
1&
x*
b00011000 .
#933
0&
#934
1&
#935
0&
#936
1&
{*
b00010101 .
#937
0&
#938
1&
b00000111 '
}*
b00000111 -
b00010011 .
#939
0&
#940
1&
{*
b00010101 .
#941
0&
#942
1&
z*
b00010110 .
#943
0&
#944
1&
b00001000 '
w*
b00001000 -
b00011001 .
#945
0&
#946
1&
x*
b00011000 .
#947
0&
#948
1&
w*
b00011001 .
#949
0&
#950
1&
t*
b00011100 .
#951
0&
#952
1&
v*
b00011010 .
#953
0&
#954
1&
u*
b00011011 .
#955
0&
#956
1&
b00001001 '
z*
b00001001 -
b00010110 .
#957
0&
#958
1&
p*
b00010000 .
#959
0&
#960
1&
s*
b00001101 .
#961
0&
#962
1&
#963
0&
#964
1&
*
b00010001 .
#965
0&
#966
1&
b00001010 '
~*
b00001010 -
b00010010 .
#967
0&
#968
1&
|*
b00010100 .
#969
0&
#970
1&
z*
b00010110 .
#971
0&
#972
1&
y*
b00010111 .
#973
0&
#974
1&
t*
b00011100 .
#975
0&
#976
1&
p*
b00100000 .
#977
0&
#978
1&
v*
b00011010 .
#979
0&
#980
1&
|*
b00010100 .
#981
0&
#982
1&
{*
b00010101 .
#983
0&
#984
1&
|*
b00010100 .
#985
0&
#986
1&
}*
b00010011 .
#987
0&
#988
1&
~*
b00010010 .
#989
0&
#990
1&
*
b00010001 .
#991
0&
#992
1&
|*
b00010100 .
#993
0&
#994
1&
}*
b00010011 .
#995
0&
#996
1&
~*
b00010010 .
#997
0&
#998
1&
}*
b00010011 .
#999
0&
#1000
1&
~*
b00010010 .
#1001
0&
#1002
1&
y*
b00010111 .
#1003
0&
#1004
1&
u*
b00011011 .
#1005
0&
#1006
1&
x*
b00011000 .
#1007
0&
#1008
1&
z*
b00010110 .
#1009
0&
#1010
1&
|*
b00010100 .
#1011
0&
#1012
1&
b00001011 '
b00001011 -
#1013
0&
#1014
1&
z*
b00010110 .
#1015
0&
#1016
1&
~*
b00010010 .
#1017
0&
#1018
1&
b00001100 '
*
b00001100 -
b00010001 .
#1019
0&
#1020
1&
p*
b00010000 .
#1021
0&
#1022
1&
r*
b00001110 .
#1023
0&
#1024
1&
b00001101 '
s*
b00001101 -
b00001101 .
#1025
0&
#1026
1&
b00001110 '
z*
b00001110 -
b00010110 .
#1027
0&
#1028
1&
b00001111 '
x*
b00001111 -
b00011000 .
#1029
0&
#1030
1&
b00010000 '
b00010000 -
#1031
0&
#1032
1&
b00010001 '
v*
b00010001 -
b00011010 .
#1033
0&
#1034
1&
s*
b00011101 .
#1035
0&
#1036
1&
r*
b00011110 .
#1037
0&
#1038
1&
w*
b00011001 .
#1039
0&
#1040
1&
t*
b00011100 .
#1041
0&
#1042
1&
s*
b00011101 .
#1043
0&
#1044
1&
~*
b00100010 .
#1045
0&
#1046
1&
*
b00100001 .
#1047
0&
#1048
1&
s*
b00011101 .
#1049
0&
#1050
1&
*
b00100001 .
#1051
0&
#1052
1&
}*
b00100011 .
#1053
0&
#1054
1&
~*
b00100010 .
#1055
0&
#1056
1&
#1057
0&
